assembly_mesh_plugin/__init__.py
assembly_mesh_plugin/plugin.py
assembly_mesh_plugin-0.1.4.dist-info/METADATA
assembly_mesh_plugin-0.1.4.dist-info/WHEEL
assembly_mesh_plugin-0.1.4.dist-info/licenses/LICENSE
assembly_mesh_plugin-0.1.4.dist-info/RECORD
