Metadata-Version: 2.4
Name: assembly_mesh_plugin
Version: 0.1.4
Summary: CadQuery plugin to create a mesh of an assembly with corresponding data
Project-URL: Repository, https://github.com/cadquery/assembly-mesh-plugin.git
Project-URL: Bug Tracker, https://github.com/cadquery/assembly-mesh-plugin/issues
Author: Jeremy Wright
Maintainer: Jeremy Wright
License:                                  Apache License
License-File: LICENSE
Keywords: CAD,cadquery,design,engineering
Classifier: Development Status :: 4 - Beta
Classifier: Programming Language :: Python
Requires-Python: >=3.9
Requires-Dist: cadquery>=2.6.0
Requires-Dist: gmsh
Provides-Extra: dev
Requires-Dist: black; extra == 'dev'
Requires-Dist: pytest; extra == 'dev'
